MANIFEST.in
README.md
setup.py
aerial_utils/__init__.py
aerial_utils/__main__.py
aerial_utils/aerial_utils.CITATION
aerial_utils/aerial_utils.LICENSE
aerial_utils/aerial_utils.VERSION
aerial_utils/util.py
aerial_utils.egg-info/PKG-INFO
aerial_utils.egg-info/SOURCES.txt
aerial_utils.egg-info/dependency_links.txt
aerial_utils.egg-info/entry_points.txt
aerial_utils.egg-info/requires.txt
aerial_utils.egg-info/top_level.txt
aerial_utils/__pycache__/__init__.cpython-311.pyc
aerial_utils/__pycache__/__main__.cpython-311.pyc
aerial_utils/__pycache__/util.cpython-311.pyc
aerial_utils/workflow/.nf-core.yml
aerial_utils/workflow/main.nf
aerial_utils/workflow/modules.json
aerial_utils/workflow/nextflow.config
aerial_utils/workflow/params.yaml
aerial_utils/workflow/modules/nf-core/bedtools/intersect/main.nf
aerial_utils/workflow/modules/nf-core/bedtools/intersect/meta.yml
aerial_utils/workflow/modules/nf-core/fastqc/main.nf
aerial_utils/workflow/modules/nf-core/fastqc/meta.yml